print/__init__.py
print/constants.py
print/div.py
print/exception.py
print/pconfig.py
print/print.py
print/putil.py
print/table.py
printtools/__init__.py
printtools/constants.py
printtools/div.py
printtools/exception.py
printtools/print.py
printtools/putil.py
printtools/table.py
printtools-2.0.1.dist-info/LICENSE
printtools-2.0.1.dist-info/METADATA
printtools-2.0.1.dist-info/WHEEL
printtools-2.0.1.dist-info/top_level.txt
printtools-2.0.1.dist-info/RECORD
