Metadata-Version: 2.1
Name: printtools
Version: 2.0.1
Summary: Collection of print utilities making heavy use of ANSI escape sequences with PyFiglet integration
Home-page: https://github.com/thetianshuhuang/print
Author: Tianshu Huang
Author-email: tianshu@cmu.edu
License: MIT
Platform: UNKNOWN
Classifier: Programming Language :: Python :: 3
Classifier: License :: OSI Approved :: MIT License
Classifier: Operating System :: OS Independent
Requires-Dist: pyfiglet
